{
  "sending_institution": "Crafton Hills College",
  "receiving_institution": "University of California, Davis",
  "major": "Sustainable Environmental Design B.S.",
  "academic_year": "2024-25",
  "url": "https://assist.org/transfer/results?year=&institution=&agreement=&agreementType=from&view=agreement&viewBy=major",
  "scraped_at": "2026-04-27T18:09:49.068350",
  "sections": [
    {
      "section_title": "PREPARATION COURSES FOR THE MAJOR",
      "groups": [
        {
          "group_id": "7d8e6845-6887-ef11-8474-000d3a37e3b6",
          "group_number": 1,
          "group_label": null,
          "group_logic": "COMPLETE_ALL",
          "select_n": null,
          "select_units": null,
          "options": [
            {
              "option_label": null,
              "rows": [
                {
                  "receiving_courses": {
                    "courses": [
                      {
                        "prefix": "BIS",
                        "number": "002B",
                        "title": "Introduction to Biology: Principles of Ecology & Evolution",
                        "units": 5.0
                      }
                    ],
                    "logic": "SINGLE"
                  },
                  "sending_courses": {
                    "courses": [
                      {
                        "prefix": "BIOL",
                        "number": "131",
                        "title": "Populations and Organisms",
                        "units": 4.0
                      },
                      {
                        "prefix": "BIOL",
                        "number": "131H",
                        "title": "Populations and Organisms - Honors",
                        "units": 4.0
                      }
                    ],
                    "logic": "SINGLE"
                  }
                }
              ]
            }
          ]
        }
      ],
      "rows": []
    },
    {
      "section_title": "ENGLISH COMPOSITION",
      "groups": [
        {
          "group_id": "678e6845-6887-ef11-8474-000d3a37e3b6",
          "group_number": 2,
          "group_label": "Complete 1 course from the following",
          "group_logic": "SELECT_N",
          "select_n": 1,
          "select_units": null,
          "options": [
            {
              "option_label": null,
              "rows": [
                {
                  "receiving_courses": {
                    "courses": [
                      {
                        "prefix": "ENL",
                        "number": "003",
                        "title": "Introduction to Literature ",
                        "units": 4.0
                      }
                    ],
                    "logic": "SINGLE"
                  },
                  "sending_courses": {
                    "courses": [
                      {
                        "prefix": "ENGL",
                        "number": "152",
                        "title": "Intermediate Composition and Literature",
                        "units": 4.0
                      },
                      {
                        "prefix": "ENGL",
                        "number": "152H",
                        "title": "Intermediate Composition and Literature - Honors",
                        "units": 4.0
                      }
                    ],
                    "logic": "SINGLE"
                  }
                },
                {
                  "receiving_courses": {
                    "courses": [
                      {
                        "prefix": "UWP",
                        "number": "001",
                        "title": "Introduction to Academic Literacies ",
                        "units": 4.0
                      }
                    ],
                    "logic": "SINGLE"
                  },
                  "sending_courses": {
                    "courses": [
                      {
                        "prefix": "ENGL",
                        "number": "101H",
                        "title": "Freshman Composition - Honors",
                        "units": 4.0
                      },
                      {
                        "prefix": "ENGL",
                        "number": "101",
                        "title": "Freshman Composition",
                        "units": 4.0
                      }
                    ],
                    "logic": "SINGLE"
                  }
                },
                {
                  "receiving_courses": {
                    "courses": [
                      {
                        "prefix": "CMN",
                        "number": "001",
                        "title": "Introduction to Public Speaking",
                        "units": 4.0
                      }
                    ],
                    "logic": "SINGLE"
                  },
                  "sending_courses": {
                    "courses": [
                      {
                        "prefix": "COMMST",
                        "number": "100H",
                        "title": "Elements of Public Speaking - Honors",
                        "units": 3.0
                      },
                      {
                        "prefix": "COMMST",
                        "number": "100",
                        "title": "Elements of Public Speaking",
                        "units": 3.0
                      }
                    ],
                    "logic": "SINGLE"
                  }
                }
              ]
            }
          ]
        }
      ],
      "rows": []
    },
    {
      "section_title": "ECONOMICS",
      "groups": [
        {
          "group_id": "778e6845-6887-ef11-8474-000d3a37e3b6",
          "group_number": 3,
          "group_label": "Complete 1 semester units from the following",
          "group_logic": "SELECT_N",
          "select_n": null,
          "select_units": 1.0,
          "options": [
            {
              "option_label": null,
              "rows": [
                {
                  "receiving_courses": {
                    "courses": [
                      {
                        "prefix": "ECN",
                        "number": "001A",
                        "title": "Principles of Microeconomics",
                        "units": 4.0
                      }
                    ],
                    "logic": "SINGLE"
                  },
                  "sending_courses": {
                    "courses": [
                      {
                        "prefix": "ECON",
                        "number": "201H",
                        "title": "Principles of Microeconomics - Honors",
                        "units": 3.0
                      },
                      {
                        "prefix": "ECON",
                        "number": "201",
                        "title": "Principles of Microeconomics",
                        "units": 3.0
                      }
                    ],
                    "logic": "SINGLE"
                  }
                },
                {
                  "receiving_courses": {
                    "courses": [
                      {
                        "prefix": "ECN",
                        "number": "001B",
                        "title": "Principles of Macroeconomics",
                        "units": 4.0
                      }
                    ],
                    "logic": "SINGLE"
                  },
                  "sending_courses": {
                    "courses": [
                      {
                        "prefix": "ECON",
                        "number": "200H",
                        "title": "Principles of Macroeconomics - Honors",
                        "units": 3.0
                      },
                      {
                        "prefix": "ECON",
                        "number": "200",
                        "title": "Principles of Macroeconomics",
                        "units": 3.0
                      }
                    ],
                    "logic": "SINGLE"
                  }
                }
              ]
            }
          ]
        }
      ],
      "rows": []
    },
    {
      "section_title": "POLITICAL SCIENCE",
      "groups": [
        {
          "group_id": "788e6845-6887-ef11-8474-000d3a37e3b6",
          "group_number": 4,
          "group_label": "Complete 1 semester units from the following",
          "group_logic": "SELECT_N",
          "select_n": null,
          "select_units": 1.0,
          "options": [
            {
              "option_label": null,
              "rows": [
                {
                  "receiving_courses": {
                    "courses": [
                      {
                        "prefix": "POL",
                        "number": "001",
                        "title": "American National Government ",
                        "units": 4.0
                      }
                    ],
                    "logic": "SINGLE"
                  },
                  "sending_courses": {
                    "courses": [
                      {
                        "prefix": "POLIT",
                        "number": "100H",
                        "title": "American Politics - Honors",
                        "units": 3.0
                      },
                      {
                        "prefix": "POLIT",
                        "number": "100",
                        "title": "American Politics",
                        "units": 3.0
                      }
                    ],
                    "logic": "SINGLE"
                  }
                },
                {
                  "receiving_courses": {
                    "courses": [
                      {
                        "prefix": "POL",
                        "number": "002",
                        "title": "Introduction to Comparative Politics ",
                        "units": 4.0
                      }
                    ],
                    "logic": "SINGLE"
                  },
                  "sending_courses": {
                    "courses": [
                      {
                        "prefix": "POLIT",
                        "number": "104",
                        "title": "Introduction to Comparative Politics",
                        "units": 3.0
                      }
                    ],
                    "logic": "SINGLE"
                  }
                },
                {
                  "receiving_courses": {
                    "courses": [
                      {
                        "prefix": "POL",
                        "number": "003",
                        "title": "International Relations ",
                        "units": 4.0
                      }
                    ],
                    "logic": "SINGLE"
                  },
                  "sending_courses": {
                    "courses": [
                      {
                        "prefix": "POLIT",
                        "number": "106",
                        "title": "Introduction to World Politics",
                        "units": 3.0
                      }
                    ],
                    "logic": "SINGLE"
                  }
                },
                {
                  "receiving_courses": {
                    "courses": [
                      {
                        "prefix": "POL",
                        "number": "004",
                        "title": "Basic Concepts in Political Theory ",
                        "units": 4.0
                      }
                    ],
                    "logic": "SINGLE"
                  },
                  "sending_courses": {
                    "courses": [
                      {
                        "prefix": "POLIT",
                        "number": "110",
                        "title": "Introduction to Political Theory",
                        "units": 3.0
                      }
                    ],
                    "logic": "SINGLE"
                  }
                }
              ]
            }
          ]
        }
      ],
      "rows": []
    },
    {
      "section_title": "SOCIOLOGY",
      "groups": [
        {
          "group_id": "768e6845-6887-ef11-8474-000d3a37e3b6",
          "group_number": 5,
          "group_label": "Complete 1 semester units from the following",
          "group_logic": "SELECT_N",
          "select_n": null,
          "select_units": 1.0,
          "options": [
            {
              "option_label": null,
              "rows": [
                {
                  "receiving_courses": {
                    "courses": [
                      {
                        "prefix": "SOC",
                        "number": "001",
                        "title": "Introduction to Sociology ",
                        "units": 5.0
                      }
                    ],
                    "logic": "SINGLE"
                  },
                  "sending_courses": {
                    "courses": [
                      {
                        "prefix": "SOC",
                        "number": "100",
                        "title": "Introduction to Sociology",
                        "units": 3.0
                      },
                      {
                        "prefix": "SOC",
                        "number": "100H",
                        "title": "Introduction to Sociology - Honors",
                        "units": 3.0
                      }
                    ],
                    "logic": "SINGLE"
                  }
                },
                {
                  "receiving_courses": {
                    "courses": [
                      {
                        "prefix": "SOC",
                        "number": "003",
                        "title": "Social Problems",
                        "units": 4.0
                      }
                    ],
                    "logic": "SINGLE"
                  },
                  "sending_courses": {
                    "courses": [
                      {
                        "prefix": "SOC",
                        "number": "105",
                        "title": "Social Problems",
                        "units": 3.0
                      }
                    ],
                    "logic": "SINGLE"
                  }
                }
              ]
            }
          ]
        }
      ],
      "rows": []
    },
    {
      "section_title": "STATISTICS",
      "groups": [
        {
          "group_id": "708e6845-6887-ef11-8474-000d3a37e3b6",
          "group_number": 6,
          "group_label": "Complete 1 semester units from the following",
          "group_logic": "SELECT_N",
          "select_n": null,
          "select_units": 1.0,
          "options": [
            {
              "option_label": null,
              "rows": [
                {
                  "receiving_courses": {
                    "courses": [
                      {
                        "prefix": "STA",
                        "number": "013",
                        "title": "Elementary Statistics",
                        "units": 4.0
                      }
                    ],
                    "logic": "SINGLE"
                  },
                  "sending_courses": {
                    "courses": [
                      {
                        "prefix": "MATH",
                        "number": "110",
                        "title": "Introduction to Probability and Statistics",
                        "units": 4.0
                      },
                      {
                        "prefix": "PSYCH",
                        "number": "120",
                        "title": "Statistics for the Social and Behavioral Sciences",
                        "units": 4.0
                      },
                      {
                        "prefix": "MATH",
                        "number": "110H",
                        "title": "Introduction to Probability and Statistics - Honors",
                        "units": 4.0
                      }
                    ],
                    "logic": "SINGLE"
                  }
                },
                {
                  "receiving_courses": {
                    "courses": [
                      {
                        "prefix": "STA",
                        "number": "015A",
                        "title": "Introduction to Statistical Data Science I ",
                        "units": 4.0
                      }
                    ],
                    "logic": "SINGLE"
                  },
                  "sending_courses": {
                    "courses": [],
                    "logic": "NO_ARTICULATION"
                  }
                },
                {
                  "receiving_courses": {
                    "courses": [
                      {
                        "prefix": "STA",
                        "number": "015B",
                        "title": "Introduction to Statistical Data Science II ",
                        "units": 4.0
                      }
                    ],
                    "logic": "SINGLE"
                  },
                  "sending_courses": {
                    "courses": [],
                    "logic": "NO_ARTICULATION"
                  }
                },
                {
                  "receiving_courses": {
                    "courses": [
                      {
                        "prefix": "STA",
                        "number": "015C",
                        "title": "Introduction to Statistical Data Science III ",
                        "units": 4.0
                      }
                    ],
                    "logic": "SINGLE"
                  },
                  "sending_courses": {
                    "courses": [],
                    "logic": "NO_ARTICULATION"
                  }
                }
              ]
            }
          ]
        }
      ],
      "rows": []
    },
    {
      "section_title": "PHYSICAL SCIENCE",
      "groups": [
        {
          "group_id": "818e6845-6887-ef11-8474-000d3a37e3b6",
          "group_number": 7,
          "group_label": "Select A, B, or C",
          "group_logic": "SELECT_ONE",
          "select_n": null,
          "select_units": null,
          "options": [
            {
              "option_label": "A",
              "rows": [
                {
                  "receiving_courses": {
                    "courses": [
                      {
                        "prefix": "CHE",
                        "number": "002A",
                        "title": "General Chemistry",
                        "units": 5.0
                      },
                      {
                        "prefix": "CHE",
                        "number": "002B",
                        "title": "General Chemistry",
                        "units": 5.0
                      },
                      {
                        "prefix": "CHE",
                        "number": "002C",
                        "title": "General Chemistry",
                        "units": 5.0
                      }
                    ],
                    "logic": "AND"
                  },
                  "sending_courses": {
                    "courses": [
                      {
                        "prefix": "CHEM",
                        "number": "150",
                        "title": "General Chemistry I",
                        "units": 5.0
                      },
                      {
                        "prefix": "CHEM",
                        "number": "151",
                        "title": "General Chemistry II",
                        "units": 5.0
                      }
                    ],
                    "logic": "AND"
                  }
                },
                {
                  "receiving_courses": {
                    "courses": [
                      {
                        "prefix": "CHE",
                        "number": "008B",
                        "title": "Organic Chemistry: Brief Course",
                        "units": 4.0
                      }
                    ],
                    "logic": "SINGLE"
                  },
                  "sending_courses": {
                    "courses": [
                      {
                        "prefix": "CHEM",
                        "number": "102",
                        "title": "Introduction to Organic Chemistry",
                        "units": 4.0
                      }
                    ],
                    "logic": "SINGLE"
                  }
                }
              ]
            },
            {
              "option_label": "B",
              "rows": [
                {
                  "receiving_courses": {
                    "courses": [
                      {
                        "prefix": "GEL",
                        "number": "001",
                        "title": "The Earth",
                        "units": 4.0
                      }
                    ],
                    "logic": "SINGLE"
                  },
                  "sending_courses": {
                    "courses": [
                      {
                        "prefix": "GEOL",
                        "number": "101",
                        "title": "Introduction to Geology",
                        "units": 3.0
                      },
                      {
                        "prefix": "GEOL",
                        "number": "100",
                        "title": "Physical Geology",
                        "units": 4.0
                      },
                      {
                        "prefix": "GEOL",
                        "number": "100H",
                        "title": "Physical Geology - Honors",
                        "units": 4.0
                      },
                      {
                        "prefix": "GEOL",
                        "number": "101H",
                        "title": "Introduction to Geology - Honors",
                        "units": 3.0
                      }
                    ],
                    "logic": "SINGLE"
                  }
                }
              ]
            },
            {
              "option_label": "C",
              "rows": [
                {
                  "receiving_courses": {
                    "courses": [
                      {
                        "prefix": "PHY",
                        "number": "007A",
                        "title": "General Physics ",
                        "units": 4.0
                      }
                    ],
                    "logic": "SINGLE"
                  },
                  "sending_courses": {
                    "courses": [
                      {
                        "prefix": "PHYSIC",
                        "number": "111",
                        "title": "General Physics II",
                        "units": 4.0
                      },
                      {
                        "prefix": "PHYSIC",
                        "number": "110",
                        "title": "General Physics I",
                        "units": 4.0
                      }
                    ],
                    "logic": "AND"
                  }
                },
                {
                  "receiving_courses": {
                    "courses": [
                      {
                        "prefix": "PHY",
                        "number": "007B",
                        "title": "General Physics ",
                        "units": 4.0
                      }
                    ],
                    "logic": "SINGLE"
                  },
                  "sending_courses": {
                    "courses": [
                      {
                        "prefix": "PHYSIC",
                        "number": "110",
                        "title": "General Physics I",
                        "units": 4.0
                      },
                      {
                        "prefix": "PHYSIC",
                        "number": "111",
                        "title": "General Physics II",
                        "units": 4.0
                      }
                    ],
                    "logic": "AND"
                  }
                },
                {
                  "receiving_courses": {
                    "courses": [
                      {
                        "prefix": "PHY",
                        "number": "007C",
                        "title": "General Physics ",
                        "units": 4.0
                      }
                    ],
                    "logic": "SINGLE"
                  },
                  "sending_courses": {
                    "courses": [
                      {
                        "prefix": "PHYSIC",
                        "number": "111",
                        "title": "General Physics II",
                        "units": 4.0
                      },
                      {
                        "prefix": "PHYSIC",
                        "number": "110",
                        "title": "General Physics I",
                        "units": 4.0
                      }
                    ],
                    "logic": "AND"
                  }
                },
                {
                  "receiving_courses": {
                    "courses": [
                      {
                        "prefix": "PHY",
                        "number": "009A",
                        "title": "Classical Physics ",
                        "units": 5.0
                      }
                    ],
                    "logic": "SINGLE"
                  },
                  "sending_courses": {
                    "courses": [
                      {
                        "prefix": "PHYSIC",
                        "number": "250",
                        "title": "College Physics I",
                        "units": 4.0
                      }
                    ],
                    "logic": "SINGLE"
                  }
                },
                {
                  "receiving_courses": {
                    "courses": [
                      {
                        "prefix": "PHY",
                        "number": "009B",
                        "title": "Classical Physics ",
                        "units": 5.0
                      }
                    ],
                    "logic": "SINGLE"
                  },
                  "sending_courses": {
                    "courses": [
                      {
                        "prefix": "PHYSIC",
                        "number": "250",
                        "title": "College Physics I",
                        "units": 4.0
                      },
                      {
                        "prefix": "PHYSIC",
                        "number": "252",
                        "title": "College Physics III",
                        "units": 4.0
                      },
                      {
                        "prefix": "PHYSIC",
                        "number": "251",
                        "title": "College Physics II",
                        "units": 4.0
                      }
                    ],
                    "logic": "AND"
                  }
                },
                {
                  "receiving_courses": {
                    "courses": [
                      {
                        "prefix": "PHY",
                        "number": "009C",
                        "title": "Classical Physics ",
                        "units": 5.0
                      }
                    ],
                    "logic": "SINGLE"
                  },
                  "sending_courses": {
                    "courses": [
                      {
                        "prefix": "PHYSIC",
                        "number": "251",
                        "title": "College Physics II",
                        "units": 4.0
                      }
                    ],
                    "logic": "SINGLE"
                  }
                },
                {
                  "receiving_courses": {
                    "courses": [
                      {
                        "prefix": "PHY",
                        "number": "010",
                        "title": "Topics in Physics for Nonscientists ",
                        "units": 4.0
                      }
                    ],
                    "logic": "SINGLE"
                  },
                  "sending_courses": {
                    "courses": [
                      {
                        "prefix": "PHYSIC",
                        "number": "100",
                        "title": "Introduction to Physics",
                        "units": 4.0
                      }
                    ],
                    "logic": "SINGLE"
                  }
                }
              ]
            }
          ]
        }
      ],
      "rows": []
    }
  ],
  "notes": [
    "Guarantee your admission to UC Davis! The UC Davis Transfer Admission Guarantee (TAG) is a written agreement ensuring your admission to UC Davis from any California Community College. Please visit the TAG webpage for more information!",
    "Transfer students are strongly encouraged to work closely with the California Community College counselors for transfer preparation to UC Davis. Transfer students may also contact a UC Davis transfer advisor for assistance. The below agreements should be utilized in conjunction with professional advising.",
    "Please note that the Department Agreements as published on ASSIST are also important documents and should be referenced in conjunction with the major agreements as needed.",
    "Graduates will choose to pursue work in government, community organizations, education, or the private sector. They will also be well-positioned to pursue graduate education in city & regional planning, landscape architecture, architecture, public policy, public administration, law, real estate, and related fields.",
    "Please refer to the Transfer Admissions Requirements for information on admissions to this major.",
    "The Sustainable Environmental Design major is intended to build student understanding and skills related to creation of sustainable communities and landscapes. Coursework emphasizes urban and environmental design, sustainable development theory & practice, green building, local government planning & decision-making, community dynamics & organizations, and written, graphic, and oral presentation of sustainability strategies. The Sustainable Environmental Design major is particularly suited for students who are interested in the physical form & design of communities and related public & private processes. It is focused on the physical environment of communities and the process of designing, planning for, and regulating the built landscape and the place-making considerations involved in creating sustainable communities."
  ]
}